pydra/tasks/petpvc/__init__.py
pydra/tasks/petpvc/petpvc.py
pydra/tasks/petpvc/specs.py
pydra/tasks/petpvc/utils.py
pydra_petpvc-0.0.4.dist-info/METADATA
pydra_petpvc-0.0.4.dist-info/WHEEL
pydra_petpvc-0.0.4.dist-info/licenses/LICENSE
pydra_petpvc-0.0.4.dist-info/RECORD
